mastersign/datascience/core/__init__.py
mastersign/datascience/database/__init__.py
mastersign/datascience/files/__init__.py
mastersign/datascience/notebook/__init__.py
mastersign/datascience/notebook/export_cell_code.py
mastersign/datascience/notebook/remove_input_from_html.py
mastersign/datascience/plot/__init__.py
mastersign/datascience/plot/basemap.py
mastersign/datascience/reversegeocoder/__init__.py
mastersign_datascience-0.3.1.dist-info/LICENSE
mastersign_datascience-0.3.1.dist-info/METADATA
mastersign_datascience-0.3.1.dist-info/WHEEL
mastersign_datascience-0.3.1.dist-info/top_level.txt
mastersign_datascience-0.3.1.dist-info/RECORD
