Metadata-Version: 2.1
Name: mastersign-datascience
Version: 0.3.1
Summary: High level helpers for data science in Python with Pandas.
Home-page: https://github.com/mastersign/mastersign-datascience.git
Author: Tobias Kiertscher
Author-email: dev@mastersign.de
Maintainer: Tobias Kiertscher
Maintainer-email: dev@mastersign.de
License: BSD-3
Keywords: lib datascience
Classifier: Development Status :: 4 - Beta
Classifier: Intended Audience :: Developers
Classifier: License :: OSI Approved :: BSD License
Classifier: Natural Language :: English
Classifier: Operating System :: OS Independent
Classifier: Programming Language :: Python
Classifier: Programming Language :: Python :: 3
Classifier: Programming Language :: Python :: 3.6
Classifier: Topic :: Software Development :: Libraries :: Python Modules
License-File: LICENSE
Requires-Dist: numpy
Requires-Dist: scipy
Requires-Dist: Pandas >=0.23
Requires-Dist: SQLAlchemy >=2.0
Requires-Dist: tabulate
Requires-Dist: matplotlib
Requires-Dist: beautifulsoup4
Requires-Dist: click >=7.0
Requires-Dist: fastparquet >=0.3
